odoo9_addon_project_task_digitized_signature-9.0.1.0.0.99.dev10-py3.8-nspkg.pth
odoo_addons/project_task_digitized_signature/README.rst
odoo_addons/project_task_digitized_signature/__init__.py
odoo_addons/project_task_digitized_signature/__openerp__.py
odoo_addons/project_task_digitized_signature/i18n/ar.po
odoo_addons/project_task_digitized_signature/i18n/ca.po
odoo_addons/project_task_digitized_signature/i18n/de.po
odoo_addons/project_task_digitized_signature/i18n/el.po
odoo_addons/project_task_digitized_signature/i18n/es.po
odoo_addons/project_task_digitized_signature/i18n/es_CR.po
odoo_addons/project_task_digitized_signature/i18n/es_MX.po
odoo_addons/project_task_digitized_signature/i18n/es_VE.po
odoo_addons/project_task_digitized_signature/i18n/fi.po
odoo_addons/project_task_digitized_signature/i18n/fr.po
odoo_addons/project_task_digitized_signature/i18n/gl.po
odoo_addons/project_task_digitized_signature/i18n/hr.po
odoo_addons/project_task_digitized_signature/i18n/hr_HR.po
odoo_addons/project_task_digitized_signature/i18n/hu.po
odoo_addons/project_task_digitized_signature/i18n/it.po
odoo_addons/project_task_digitized_signature/i18n/ja.po
odoo_addons/project_task_digitized_signature/i18n/lt.po
odoo_addons/project_task_digitized_signature/i18n/lv.po
odoo_addons/project_task_digitized_signature/i18n/mk.po
odoo_addons/project_task_digitized_signature/i18n/mn.po
odoo_addons/project_task_digitized_signature/i18n/nl.po
odoo_addons/project_task_digitized_signature/i18n/pl.po
odoo_addons/project_task_digitized_signature/i18n/project_task_digitized_signature.pot
odoo_addons/project_task_digitized_signature/i18n/pt.po
odoo_addons/project_task_digitized_signature/i18n/pt_BR.po
odoo_addons/project_task_digitized_signature/i18n/pt_PT.po
odoo_addons/project_task_digitized_signature/i18n/ro.po
odoo_addons/project_task_digitized_signature/i18n/sl.po
odoo_addons/project_task_digitized_signature/i18n/sv.po
odoo_addons/project_task_digitized_signature/i18n/tr.po
odoo9_addon_project_task_digitized_signature-9.0.1.0.0.99.dev10.dist-info/METADATA
odoo9_addon_project_task_digitized_signature-9.0.1.0.0.99.dev10.dist-info/WHEEL
odoo9_addon_project_task_digitized_signature-9.0.1.0.0.99.dev10.dist-info/namespace_packages.txt
odoo9_addon_project_task_digitized_signature-9.0.1.0.0.99.dev10.dist-info/top_level.txt
odoo9_addon_project_task_digitized_signature-9.0.1.0.0.99.dev10.dist-info/RECORD
