Metadata-Version: 2.1
Name: odoo9-addon-project-task-digitized-signature
Version: 9.0.1.0.0.99.dev10
Summary: Project Task Digitized Signature
Home-page: https://www.tecnativa.com
Author: Tecnativa, Odoo Community Association (OCA)
Author-email: support@odoo-community.org
License: AGPL-3
Platform: UNKNOWN
Classifier: Programming Language :: Python
Classifier: Framework :: Odoo
Classifier: Framework :: Odoo :: 9.0
Classifier: License :: OSI Approved :: GNU Affero General Public License v3
Requires-Python: ~=2.7
Requires-Dist: odoo9-addon-project-task-report
Requires-Dist: odoo9-addon-web-widget-digitized-signature
Requires-Dist: odoo (<9.1a,>=9.0a)
